{
    "docker": {
        "container": {
            "ports": [
                {
                    "container": 8888,
                    "host": 8888,
                    "test": true
                }
            ],
            "volumes": [
                {
                    "container": "/root/corpus",
                    "host": "./corpus"
                },
                {
                    "container": "/root/models",
                    "host": "./models"
                },
                {
                    "container": "/root/scripts",
                    "host": "./scripts"
                },
                {
                    "container": "/root/downloads",
                    "host": "./downloads"
                }
            ]
        },
        "image": {
            "name": "env-python",
            "tag_with_date": true,
            "version": "1.0.2"
        },
        "username": "joris"
    },
    "service": {
        "filesystem": [
            {
                "on_setup": true,
                "path": "corpus",
                "type": "folder"
            },
            {
                "on_setup": true,
                "path": "models",
                "type": "folder"
            },
            {
                "on_setup": true,
                "path": "scripts",
                "type": "folder"
            },
            {
                "on_setup": true,
                "path": "downloads",
                "type": "folder"
            }
        ]
    },
    "version_control": {
        "root_folder": "$BASE_DIR",
        "type": "git"
    }
}